djpsa/__init__.py
djpsa/manage.py
djpsa/utils.py
djpsa/api/__init__.py
djpsa/api/api_conditions.py
djpsa/api/client.py
djpsa/api/exceptions.py
djpsa/api/tests/__init__.py
djpsa/api/tests/test_api.py
djpsa/halo/__init__.py
djpsa/halo/admin.py
djpsa/halo/api.py
djpsa/halo/apps.py
djpsa/halo/callbacks.py
djpsa/halo/models.py
djpsa/halo/provider.py
djpsa/halo/sync.py
djpsa/halo/urls.py
djpsa/halo/views.py
djpsa/halo/management/__init__.py
djpsa/halo/management/commands/__init__.py
djpsa/halo/management/commands/sync.py
djpsa/halo/migrations/0001_initial.py
djpsa/halo/migrations/0002_rename_isdisabled_agent_is_disabled_and_more.py
djpsa/halo/migrations/0003_alter_ticket_agent_alter_ticket_client_and_more.py
djpsa/halo/migrations/0004_alter_agent_options_alter_client_options_and_more.py
djpsa/halo/migrations/0005_sla_site_halouser_ticket_sla.py
djpsa/halo/migrations/0006_remove_sla_hours_are_local_time.py
djpsa/halo/migrations/0007_alter_sla_track_sla_fix_by_time_and_more.py
djpsa/halo/migrations/0008_alter_site_delivery_address.py
djpsa/halo/migrations/0009_alter_halouser_options_alter_site_options_and_more.py
djpsa/halo/migrations/0010_agenttracker_appointmenttracker_clienttracker_and_more.py
djpsa/halo/migrations/0011_tickettype_remove_project_agent_and_more.py
djpsa/halo/migrations/0012_alter_client_main_site.py
djpsa/halo/migrations/0013_remove_ticket_start_time_remove_ticket_target_time_and_more.py
djpsa/halo/migrations/0014_alter_action_project_alter_action_ticket.py
djpsa/halo/migrations/0015_alter_ticket_details_alter_ticket_email_to_list_and_more.py
djpsa/halo/migrations/0016_alter_appointment_site_alter_client_main_site_and_more.py
djpsa/halo/migrations/0017_team_teamtracker.py
djpsa/halo/migrations/0018_agent_teams.py
djpsa/halo/migrations/0019_alter_ticket_team.py
djpsa/halo/migrations/0020_budgettype_ticket_itil_request_type_budgetdata_and_more.py
djpsa/halo/migrations/0021_alter_budgetdata_options.py
djpsa/halo/migrations/0022_alter_budgetdata_ticket.py
django_psa-0.18.1a0.dist-info/LICENSE
django_psa-0.18.1a0.dist-info/METADATA
django_psa-0.18.1a0.dist-info/WHEEL
django_psa-0.18.1a0.dist-info/top_level.txt
django_psa-0.18.1a0.dist-info/RECORD
