Metadata-Version: 2.1
Name: django-psa
Version: 0.18.1a0
Summary: Django app for working with various PSA REST API. Defines models (tickets, companies, etc.) and callbacks. 
Home-page: https://github.com/topleft-team/django-psa
Author: TopLeft Technologies Ltd.
Author-email: sam@topleft.team
License: MIT
Keywords: django connectwise halo autotask rest api python
Classifier: Environment :: Web Environment
Classifier: Framework :: Django
Classifier: Intended Audience :: Developers
Classifier: License :: OSI Approved :: MIT License
Classifier: Operating System :: OS Independent
Classifier: Programming Language :: Python
Classifier: Programming Language :: Python :: 3
Classifier: Topic :: Internet :: WWW/HTTP
Classifier: Topic :: Internet :: WWW/HTTP :: Dynamic Content
Classifier: Development Status :: 3 - Alpha
License-File: LICENSE
Requires-Dist: requests
Requires-Dist: django
Requires-Dist: setuptools
Requires-Dist: python-dateutil
Requires-Dist: retrying
Requires-Dist: redis
